flatbuffers/__init__.py
flatbuffers/builder.py
flatbuffers/compat.py
flatbuffers/encode.py
flatbuffers/number_types.py
flatbuffers/packer.py
flatbuffers/table.py
neodroidflatbuffers-20180620125207.dist-info/METADATA
neodroidflatbuffers-20180620125207.dist-info/RECORD
neodroidflatbuffers-20180620125207.dist-info/WHEEL
neodroidflatbuffers-20180620125207.dist-info/top_level.txt
