Metadata-Version: 2.1
Name: neodroidflatbuffers
Version: 20180620125207
Summary: The FlatBuffers serialization format for Python
Home-page: https://github.com/sintefneodroid/flatbuffers
Author: FlatBuffers Contributors
Author-email: chrini13@student.aau.dk, me@rwinslow.com
License: Apache 2.0
Platform: UNKNOWN
